{
  "version": 1,
  "skills": {
    "triple-memory": {
      "version": "1.0.0",
      "installedAt": 1771755502494
    },
    "openwork": {
      "version": "2.4.1",
      "installedAt": 1771755504073
    },
    "proactive-agent": {
      "version": "3.1.0",
      "installedAt": 1771755506066
    },
    "base-trader": {
      "version": "1.1.1",
      "installedAt": 1771755508375
    },
    "agent-browser": {
      "version": "0.2.0",
      "installedAt": 1771755509685
    },
    "deep-research-pro": {
      "version": "1.0.2",
      "installedAt": 1771755557980
    },
    "exa": {
      "version": "0.0.2",
      "installedAt": 1771755559889
    },
    "cron-mastery": {
      "version": "1.0.3",
      "installedAt": 1771755561576
    },
    "planning-with-files": {
      "version": "1.2.0",
      "installedAt": 1771755563798
    },
    "defi-yield-scanner": {
      "version": "1.0.0",
      "installedAt": 1771755565476
    },
    "git-notes-memory": {
      "version": "1.0.0",
      "installedAt": 1771758361069
    },
    "memory-manager": {
      "version": "1.0.0",
      "installedAt": 1771834165795
    }
  }
}
